{
  "scores": [
    {
      "id": 3,
      "name": "test",
      "score": 10000,
      "dateTime": "2023-12-23T21:31:16.223Z"
    },
    {
      "id": 3,
      "name": "test",
      "score": 10000,
      "dateTime": "2023-12-23T21:34:31.996Z"
    },
    {
      "id": 3,
      "name": "test",
      "score": 10000,
      "dateTime": "2023-12-23T21:38:52.169Z"
    },
    {
      "id": 3,
      "name": "test",
      "score": 10000,
      "dateTime": "2023-12-23T21:38:52.898Z"
    },
    {
      "id": 3,
      "name": "test",
      "score": 10000,
      "dateTime": "2023-12-23T21:38:53.429Z"
    },
    {
      "id": 3,
      "name": "test",
      "score": 10000,
      "dateTime": "2023-12-23T21:49:25.574Z"
    },
    {
      "id": 3,
      "name": "test",
      "score": 10000,
      "dateTime": "2023-12-23T21:49:26.342Z"
    },
    {
      "id": 1,
      "name": "Test",
      "score": 100,
      "dateTime": "2023-12-23T21:11:58.009Z"
    },
    {
      "id": 3,
      "name": "mec",
      "score": 55,
      "dateTime": "2023-12-23T21:17:19.780Z"
    },
    {
      "id": 3,
      "name": "mondher",
      "score": 55,
      "dateTime": "2023-12-23T21:17:52.413Z"
    },
    {
      "id": 2,
      "name": "mondher",
      "score": 25,
      "dateTime": "2023-12-23T21:14:23.449Z"
    }
  ]
}